rctl/__init__.py
rctl/__main__.py
rctl/_io.py
rctl/api.py
rctl/base.py
rctl/base2.py
rctl/core.py
rctl/exceptions.py
rctl/registry.py
rctl/scanner.py
rctl/app/__init__.py
rctl/backends/__init__.py
rctl/backends/backends.py
rctl/cli/__init__.py
rctl/cli/_main.py
rctl/cli/core.py
rctl/cli/resource.py
rctl/connectors/__init__.py
rctl/connectors/connection_mapping.py
rctl/modules/__init__.py
rctl/modules/_boto3.py
rctl/modules/_fsspec.py
rctl/modules/_psycopg2.py
rctl/modules/_risingwave.py
rctl/modules/mock.py
rctl/remote/__init__.py
rctl/remote/agent.py
rctl/remote/agentless.py
rctl-0.1.9.dist-info/METADATA
rctl-0.1.9.dist-info/WHEEL
rctl-0.1.9.dist-info/entry_points.txt
rctl-0.1.9.dist-info/top_level.txt
rctl-0.1.9.dist-info/RECORD
