Metadata-Version: 2.2
Name: rctl
Version: 0.1.9
Summary: Add your description here
Requires-Python: >=3.12
Requires-Dist: pyyaml>=6.0.2
Requires-Dist: fsspec>=2025.2.0
Requires-Dist: jinja2>=3.1.5
Requires-Dist: pydantic>=2.10.6
Requires-Dist: s3fs>=2025.2.0
Requires-Dist: boto3>=1.36.23
Requires-Dist: s3transfer>=0.11.2
Requires-Dist: typer>=0.15.1
Requires-Dist: psycopg2-binary==2.9.9
Requires-Dist: risingwave-py>=0.0.1
Requires-Dist: python-hcl2>=6.1.1
